{
  "formatVersion": 1,
  "database": {
    "version": 13,
    "identityHash": "fa768d0f090489a68b5f77a30183983b",
    "entities": [
      {
        "tableName": "Song",
        "createSql": "CREATE TABLE IF NOT EXISTS `${TABLE_NAME}` (`id` TEXT NOT NULL, `title` TEXT NOT NULL, `artistsText` TEXT NOT NULL, `albumId` TEXT, `durationText` TEXT NOT NULL, `thumbnailUrl` TEXT NOT NULL, `likedAt` INTEGER, `totalPlayTimeMs` INTEGER NOT NULL, PRIMARY KEY(`id`))",
        "fields": [
          {
            "fieldPath": "id",
            "columnName": "id",
            "affinity": "TEXT",
            "notNull": true
          },
          {
            "fieldPath": "title",
            "columnName": "title",
            "affinity": "TEXT",
            "notNull": true
          },
          {
            "fieldPath": "artists",
            "columnName": "artistsText",
            "affinity": "TEXT",
            "notNull": true
          },
          {
            "fieldPath": "albumId",
            "columnName": "albumId",
            "affinity": "TEXT"
          },
          {
            "fieldPath": "duration",
            "columnName": "durationText",
            "affinity": "TEXT",
            "notNull": true
          },
          {
            "fieldPath": "thumbnail",
            "columnName": "thumbnailUrl",
            "affinity": "TEXT",
            "notNull": true
          },
          {
            "fieldPath": "likedAt",
            "columnName": "likedAt",
            "affinity": "INTEGER"
          },
          {
            "fieldPath": "totalPlayTimeMs",
            "columnName": "totalPlayTimeMs",
            "affinity": "INTEGER",
            "notNull": true
          }
        ],
        "primaryKey": {
          "autoGenerate": false,
          "columnNames": [
            "id"
          ]
        }
      },
      {
        "tableName": "persisted_playback_queue",
        "createSql": "CREATE TABLE IF NOT EXISTS `${TABLE_NAME}` (`persistenceId` INTEGER PRIMARY KEY AUTOINCREMENT NOT NULL, `mediaSessionQueueId` INTEGER NOT NULL, `mediaId` TEXT NOT NULL, `positionInQueue` INTEGER NOT NULL, FOREIGN KEY(`mediaId`) REFERENCES `Song`(`id`) ON UPDATE NO ACTION ON DELETE CASCADE )",
        "fields": [
          {
            "fieldPath": "persistenceId",
            "columnName": "persistenceId",
            "affinity": "INTEGER",
            "notNull": true
          },
          {
            "fieldPath": "mediaSessionQueueId",
            "columnName": "mediaSessionQueueId",
            "affinity": "INTEGER",
            "notNull": true
          },
          {
            "fieldPath": "mediaId",
            "columnName": "mediaId",
            "affinity": "TEXT",
            "notNull": true
          },
          {
            "fieldPath": "positionInQueue",
            "columnName": "positionInQueue",
            "affinity": "INTEGER",
            "notNull": true
          }
        ],
        "primaryKey": {
          "autoGenerate": true,
          "columnNames": [
            "persistenceId"
          ]
        },
        "indices": [
          {
            "name": "index_persisted_playback_queue_mediaId",
            "unique": false,
            "columnNames": [
              "mediaId"
            ],
            "orders": [],
            "createSql": "CREATE INDEX IF NOT EXISTS `index_persisted_playback_queue_mediaId` ON `${TABLE_NAME}` (`mediaId`)"
          }
        ],
        "foreignKeys": [
          {
            "table": "Song",
            "onDelete": "CASCADE",
            "onUpdate": "NO ACTION",
            "columns": [
              "mediaId"
            ],
            "referencedColumns": [
              "id"
            ]
          }
        ]
      },
      {
        "tableName": "SearchQuery",
        "createSql": "CREATE TABLE IF NOT EXISTS `${TABLE_NAME}` (`id` TEXT NOT NULL, `query` TEXT NOT NULL, `timestamp` INTEGER NOT NULL, PRIMARY KEY(`id`))",
        "fields": [
          {
            "fieldPath": "id",
            "columnName": "id",
            "affinity": "TEXT",
            "notNull": true
          },
          {
            "fieldPath": "query",
            "columnName": "query",
            "affinity": "TEXT",
            "notNull": true
          },
          {
            "fieldPath": "timestamp",
            "columnName": "timestamp",
            "affinity": "INTEGER",
            "notNull": true
          }
        ],
        "primaryKey": {
          "autoGenerate": false,
          "columnNames": [
            "id"
          ]
        }
      },
      {
        "tableName": "Playlist",
        "createSql": "CREATE TABLE IF NOT EXISTS `${TABLE_NAME}` (`id` INTEGER PRIMARY KEY AUTOINCREMENT NOT NULL, `name` TEXT NOT NULL, `browseId` TEXT, `isEditable` INTEGER NOT NULL, `isYoutubePlaylist` INTEGER NOT NULL)",
        "fields": [
          {
            "fieldPath": "id",
            "columnName": "id",
            "affinity": "INTEGER",
            "notNull": true
          },
          {
            "fieldPath": "name",
            "columnName": "name",
            "affinity": "TEXT",
            "notNull": true
          },
          {
            "fieldPath": "browseId",
            "columnName": "browseId",
            "affinity": "TEXT"
          },
          {
            "fieldPath": "isEditable",
            "columnName": "isEditable",
            "affinity": "INTEGER",
            "notNull": true
          },
          {
            "fieldPath": "isYoutubePlaylist",
            "columnName": "isYoutubePlaylist",
            "affinity": "INTEGER",
            "notNull": true
          }
        ],
        "primaryKey": {
          "autoGenerate": true,
          "columnNames": [
            "id"
          ]
        }
      },
      {
        "tableName": "SongPlaylistMap",
        "createSql": "CREATE TABLE IF NOT EXISTS `${TABLE_NAME}` (`songId` TEXT NOT NULL, `playlistId` INTEGER NOT NULL, `position` INTEGER NOT NULL DEFAULT 0, PRIMARY KEY(`songId`, `playlistId`), FOREIGN KEY(`songId`) REFERENCES `Song`(`id`) ON UPDATE NO ACTION ON DELETE CASCADE , FOREIGN KEY(`playlistId`) REFERENCES `Playlist`(`id`) ON UPDATE NO ACTION ON DELETE CASCADE )",
        "fields": [
          {
            "fieldPath": "songId",
            "columnName": "songId",
            "affinity": "TEXT",
            "notNull": true
          },
          {
            "fieldPath": "playlistId",
            "columnName": "playlistId",
            "affinity": "INTEGER",
            "notNull": true
          },
          {
            "fieldPath": "position",
            "columnName": "position",
            "affinity": "INTEGER",
            "notNull": true,
            "defaultValue": "0"
          }
        ],
        "primaryKey": {
          "autoGenerate": false,
          "columnNames": [
            "songId",
            "playlistId"
          ]
        },
        "indices": [
          {
            "name": "index_SongPlaylistMap_songId",
            "unique": false,
            "columnNames": [
              "songId"
            ],
            "orders": [],
            "createSql": "CREATE INDEX IF NOT EXISTS `index_SongPlaylistMap_songId` ON `${TABLE_NAME}` (`songId`)"
          },
          {
            "name": "index_SongPlaylistMap_playlistId",
            "unique": false,
            "columnNames": [
              "playlistId"
            ],
            "orders": [],
            "createSql": "CREATE INDEX IF NOT EXISTS `index_SongPlaylistMap_playlistId` ON `${TABLE_NAME}` (`playlistId`)"
          }
        ],
        "foreignKeys": [
          {
            "table": "Song",
            "onDelete": "CASCADE",
            "onUpdate": "NO ACTION",
            "columns": [
              "songId"
            ],
            "referencedColumns": [
              "id"
            ]
          },
          {
            "table": "Playlist",
            "onDelete": "CASCADE",
            "onUpdate": "NO ACTION",
            "columns": [
              "playlistId"
            ],
            "referencedColumns": [
              "id"
            ]
          }
        ]
      },
      {
        "tableName": "Album",
        "createSql": "CREATE TABLE IF NOT EXISTS `${TABLE_NAME}` (`id` TEXT NOT NULL, `title` TEXT NOT NULL, `artist` TEXT NOT NULL, `thumbnailUrl` TEXT NOT NULL, `year` TEXT NOT NULL, `authorsText` TEXT NOT NULL, `copyright` TEXT NOT NULL, `shareUrl` TEXT NOT NULL, `timestamp` INTEGER, `bookmarkedAt` INTEGER, `isYoutubeAlbum` INTEGER NOT NULL, PRIMARY KEY(`id`))",
        "fields": [
          {
            "fieldPath": "id",
            "columnName": "id",
            "affinity": "TEXT",
            "notNull": true
          },
          {
            "fieldPath": "title",
            "columnName": "title",
            "affinity": "TEXT",
            "notNull": true
          },
          {
            "fieldPath": "artist",
            "columnName": "artist",
            "affinity": "TEXT",
            "notNull": true
          },
          {
            "fieldPath": "thumbnailUrl",
            "columnName": "thumbnailUrl",
            "affinity": "TEXT",
            "notNull": true
          },
          {
            "fieldPath": "year",
            "columnName": "year",
            "affinity": "TEXT",
            "notNull": true
          },
          {
            "fieldPath": "authorsText",
            "columnName": "authorsText",
            "affinity": "TEXT",
            "notNull": true
          },
          {
            "fieldPath": "copyright",
            "columnName": "copyright",
            "affinity": "TEXT",
            "notNull": true
          },
          {
            "fieldPath": "shareUrl",
            "columnName": "shareUrl",
            "affinity": "TEXT",
            "notNull": true
          },
          {
            "fieldPath": "timestamp",
            "columnName": "timestamp",
            "affinity": "INTEGER"
          },
          {
            "fieldPath": "bookmarkedAt",
            "columnName": "bookmarkedAt",
            "affinity": "INTEGER"
          },
          {
            "fieldPath": "isYoutubeAlbum",
            "columnName": "isYoutubeAlbum",
            "affinity": "INTEGER",
            "notNull": true
          }
        ],
        "primaryKey": {
          "autoGenerate": false,
          "columnNames": [
            "id"
          ]
        }
      },
      {
        "tableName": "SongAlbumMap",
        "createSql": "CREATE TABLE IF NOT EXISTS `${TABLE_NAME}` (`songId` TEXT NOT NULL, `albumId` TEXT NOT NULL, `position` INTEGER NOT NULL, PRIMARY KEY(`songId`, `albumId`), FOREIGN KEY(`songId`) REFERENCES `Song`(`id`) ON UPDATE NO ACTION ON DELETE CASCADE , FOREIGN KEY(`albumId`) REFERENCES `Album`(`id`) ON UPDATE NO ACTION ON DELETE CASCADE )",
        "fields": [
          {
            "fieldPath": "songId",
            "columnName": "songId",
            "affinity": "TEXT",
            "notNull": true
          },
          {
            "fieldPath": "albumId",
            "columnName": "albumId",
            "affinity": "TEXT",
            "notNull": true
          },
          {
            "fieldPath": "position",
            "columnName": "position",
            "affinity": "INTEGER",
            "notNull": true
          }
        ],
        "primaryKey": {
          "autoGenerate": false,
          "columnNames": [
            "songId",
            "albumId"
          ]
        },
        "indices": [
          {
            "name": "index_SongAlbumMap_songId",
            "unique": false,
            "columnNames": [
              "songId"
            ],
            "orders": [],
            "createSql": "CREATE INDEX IF NOT EXISTS `index_SongAlbumMap_songId` ON `${TABLE_NAME}` (`songId`)"
          },
          {
            "name": "index_SongAlbumMap_albumId",
            "unique": false,
            "columnNames": [
              "albumId"
            ],
            "orders": [],
            "createSql": "CREATE INDEX IF NOT EXISTS `index_SongAlbumMap_albumId` ON `${TABLE_NAME}` (`albumId`)"
          }
        ],
        "foreignKeys": [
          {
            "table": "Song",
            "onDelete": "CASCADE",
            "onUpdate": "NO ACTION",
            "columns": [
              "songId"
            ],
            "referencedColumns": [
              "id"
            ]
          },
          {
            "table": "Album",
            "onDelete": "CASCADE",
            "onUpdate": "NO ACTION",
            "columns": [
              "albumId"
            ],
            "referencedColumns": [
              "id"
            ]
          }
        ]
      },
      {
        "tableName": "Artist",
        "createSql": "CREATE TABLE IF NOT EXISTS `${TABLE_NAME}` (`id` TEXT NOT NULL, `name` TEXT NOT NULL, `thumbnailUrl` TEXT NOT NULL, `subscriber` TEXT, `description` TEXT, `timestamp` INTEGER, `bookmarkedAt` INTEGER, `isYoutubeArtist` INTEGER NOT NULL, PRIMARY KEY(`id`))",
        "fields": [
          {
            "fieldPath": "id",
            "columnName": "id",
            "affinity": "TEXT",
            "notNull": true
          },
          {
            "fieldPath": "name",
            "columnName": "name",
            "affinity": "TEXT",
            "notNull": true
          },
          {
            "fieldPath": "thumbnailUrl",
            "columnName": "thumbnailUrl",
            "affinity": "TEXT",
            "notNull": true
          },
          {
            "fieldPath": "subscriber",
            "columnName": "subscriber",
            "affinity": "TEXT"
          },
          {
            "fieldPath": "description",
            "columnName": "description",
            "affinity": "TEXT"
          },
          {
            "fieldPath": "timestamp",
            "columnName": "timestamp",
            "affinity": "INTEGER"
          },
          {
            "fieldPath": "bookmarkedAt",
            "columnName": "bookmarkedAt",
            "affinity": "INTEGER"
          },
          {
            "fieldPath": "isYoutubeArtist",
            "columnName": "isYoutubeArtist",
            "affinity": "INTEGER",
            "notNull": true
          }
        ],
        "primaryKey": {
          "autoGenerate": false,
          "columnNames": [
            "id"
          ]
        }
      },
      {
        "tableName": "GithubRelease",
        "createSql": "CREATE TABLE IF NOT EXISTS `${TABLE_NAME}` (`htmlUrl` TEXT NOT NULL, `tagName` TEXT NOT NULL, `id` INTEGER NOT NULL, `name` TEXT, `draft` INTEGER NOT NULL, `preRelease` INTEGER NOT NULL, `createdAt` TEXT NOT NULL, `publishedAt` TEXT NOT NULL, `assets` TEXT NOT NULL, `body` TEXT NOT NULL, PRIMARY KEY(`id`))",
        "fields": [
          {
            "fieldPath": "htmlUrl",
            "columnName": "htmlUrl",
            "affinity": "TEXT",
            "notNull": true
          },
          {
            "fieldPath": "tagName",
            "columnName": "tagName",
            "affinity": "TEXT",
            "notNull": true
          },
          {
            "fieldPath": "id",
            "columnName": "id",
            "affinity": "INTEGER",
            "notNull": true
          },
          {
            "fieldPath": "name",
            "columnName": "name",
            "affinity": "TEXT"
          },
          {
            "fieldPath": "draft",
            "columnName": "draft",
            "affinity": "INTEGER",
            "notNull": true
          },
          {
            "fieldPath": "preRelease",
            "columnName": "preRelease",
            "affinity": "INTEGER",
            "notNull": true
          },
          {
            "fieldPath": "createdAt",
            "columnName": "createdAt",
            "affinity": "TEXT",
            "notNull": true
          },
          {
            "fieldPath": "publishedAt",
            "columnName": "publishedAt",
            "affinity": "TEXT",
            "notNull": true
          },
          {
            "fieldPath": "assets",
            "columnName": "assets",
            "affinity": "TEXT",
            "notNull": true
          },
          {
            "fieldPath": "body",
            "columnName": "body",
            "affinity": "TEXT",
            "notNull": true
          }
        ],
        "primaryKey": {
          "autoGenerate": false,
          "columnNames": [
            "id"
          ]
        }
      }
    ],
    "setupQueries": [
      "CREATE TABLE IF NOT EXISTS room_master_table (id INTEGER PRIMARY KEY,identity_hash TEXT)",
      "INSERT OR REPLACE INTO room_master_table (id,identity_hash) VALUES(42, 'fa768d0f090489a68b5f77a30183983b')"
    ]
  }
}